navsim/__init__.py
navsim/archived_code.py
navsim/cli_utils.py
navsim/init_consistency_test.py
navsim/main.py
navsim/memory.py
navsim/version.txt
navsim/agent/__init__.py
navsim/agent/ddpg.py
navsim/agent/nn.py
navsim/benchmarks/__init__.py
navsim/benchmarks/benchmark.py
navsim/benchmarks/saturate_gpu.py
navsim/executor/__init__.py
navsim/executor/navsim_executor.py
navsim/executor/ray_executor.py
navsim/tests/__init__.py
navsim/tests/test_torch.py
navsim/util/__init__.py
navsim/util/conf.py
navsim/util/dict.py
navsim/util/env_utils.py
navsim/util/resources.py
navsim/util/util.py
navsim-2.10.7.dist-info/METADATA
navsim-2.10.7.dist-info/WHEEL
navsim-2.10.7.dist-info/entry_points.txt
navsim-2.10.7.dist-info/top_level.txt
navsim-2.10.7.dist-info/RECORD
