Metadata-Version: 2.1
Name: navsim
Version: 2.10.7
Summary: Navigation Simulator
Home-page: UNKNOWN
Author: STTC, IST, UCF
Author-email: armando@ucf.edu
License: UNKNOWN
Platform: UNKNOWN
Classifier: Programming Language :: Python :: 3
Classifier: License :: OSI Approved :: Apache Software License
Classifier: Operating System :: OS Independent
Classifier: Topic :: Scientific/Engineering
Classifier: Topic :: Scientific/Engineering :: Mathematics
Classifier: Topic :: Scientific/Engineering :: Artificial Intelligence
Classifier: Topic :: Software Development
Classifier: Topic :: Software Development :: Libraries
Classifier: Intended Audience :: Developers
Classifier: Intended Audience :: Education
Classifier: Intended Audience :: Science/Research
Requires-Python: >=3.7
Requires-Dist: navsim-envs
Requires-Dist: numpy
Requires-Dist: gym (>=0.18.0)
Requires-Dist: mlagents (==0.27.0)
Requires-Dist: mlagents-envs (==0.27.0)
Requires-Dist: gym-unity (==0.27.0)
